<?xml version="1.0" encoding="UTF-8"?>
<definitions xmlns="http://www.omg.org/spec/BPMN/20100524/MODEL" xmlns:xsi="http://www.w3.org/2001/XMLSchema-instance" xmlns:xsd="http://www.w3.org/2001/XMLSchema" xmlns:activiti="http://activiti.org/bpmn" xmlns:bpmndi="http://www.omg.org/spec/BPMN/20100524/DI" xmlns:omgdc="http://www.omg.org/spec/DD/20100524/DC" xmlns:omgdi="http://www.omg.org/spec/DD/20100524/DI" xmlns:flowable="http://flowable.org/bpmn" typeLanguage="http://www.w3.org/2001/XMLSchema" expressionLanguage="http://www.w3.org/1999/XPath" targetNamespace="http://www.flowable.org/processdef">
  <process id="multiInstance" name="multiInstance" isExecutable="true">
    <documentation>multiInstance</documentation>
    <startEvent id="startEvent1"></startEvent>
    <userTask id="A" name="多实例测试" xmlns:flowable="http://flowable.org/bpmn" flowable:candidateUsers="shareniu1,shareniu2,shareniu3,shareniu4">
      <multiInstanceLoopCharacteristics isSequential="false">
        <loopCardinality>2</loopCardinality>
      </multiInstanceLoopCharacteristics>
    </userTask>
    <sequenceFlow id="sid-6D482A8A-F796-4E2B-AB2C-ABBFD2DA428D" sourceRef="startEvent1" targetRef="A"></sequenceFlow>
    <userTask id="shareniu-B" name="shareniu-B" xmlns:shareniu="http://www.shareniu.com/" shareniu:shareniuext="" shareniu:shareniuextboolen="false"></userTask>
    <sequenceFlow id="sid-BA8FC337-40DC-493B-805C-F213B7C4A17D" sourceRef="A" targetRef="shareniu-B"></sequenceFlow>
    <userTask id="shareniu-C" name="shareniu-C"></userTask>
    <sequenceFlow id="flow1" sourceRef="shareniu-B" targetRef="shareniu-C"></sequenceFlow>
    <endEvent id="endevent1" name="End"></endEvent>
    <sequenceFlow id="flow2" sourceRef="shareniu-C" targetRef="endevent1"></sequenceFlow>
  </process>
  <bpmndi:BPMNDiagram id="BPMNDiagram_multiInstance">
    <bpmndi:BPMNPlane bpmnElement="multiInstance" id="BPMNPlane_multiInstance">
      <bpmndi:BPMNShape bpmnElement="startEvent1" id="BPMNShape_startEvent1">
        <omgdc:Bounds height="35.0" width="35.0" x="100.0" y="130.0"></omgdc:Bounds>
      </bpmndi:BPMNShape>
      <bpmndi:BPMNShape bpmnElement="A" id="BPMNShape_A">
        <omgdc:Bounds height="80.0" width="100.0" x="165.0" y="105.0"></omgdc:Bounds>
      </bpmndi:BPMNShape>
      <bpmndi:BPMNShape bpmnElement="shareniu-B" id="BPMNShape_shareniu-B">
        <omgdc:Bounds height="80.0" width="100.0" x="315.0" y="105.0"></omgdc:Bounds>
      </bpmndi:BPMNShape>
      <bpmndi:BPMNShape bpmnElement="shareniu-C" id="BPMNShape_shareniu-C">
        <omgdc:Bounds height="55.0" width="105.0" x="460.0" y="118.0"></omgdc:Bounds>
      </bpmndi:BPMNShape>
      <bpmndi:BPMNShape bpmnElement="endevent1" id="BPMNShape_endevent1">
        <omgdc:Bounds height="35.0" width="35.0" x="610.0" y="128.0"></omgdc:Bounds>
      </bpmndi:BPMNShape>
      <bpmndi:BPMNEdge bpmnElement="sid-6D482A8A-F796-4E2B-AB2C-ABBFD2DA428D" id="BPMNEdge_sid-6D482A8A-F796-4E2B-AB2C-ABBFD2DA428D">
        <omgdi:waypoint x="135.0" y="147.0"></omgdi:waypoint>
        <omgdi:waypoint x="165.0" y="145.0"></omgdi:waypoint>
      </bpmndi:BPMNEdge>
      <bpmndi:BPMNEdge bpmnElement="sid-BA8FC337-40DC-493B-805C-F213B7C4A17D" id="BPMNEdge_sid-BA8FC337-40DC-493B-805C-F213B7C4A17D">
        <omgdi:waypoint x="265.0" y="145.0"></omgdi:waypoint>
        <omgdi:waypoint x="290.0" y="145.0"></omgdi:waypoint>
        <omgdi:waypoint x="290.0" y="160.0"></omgdi:waypoint>
        <omgdi:waypoint x="315.0" y="145.0"></omgdi:waypoint>
      </bpmndi:BPMNEdge>
      <bpmndi:BPMNEdge bpmnElement="flow1" id="BPMNEdge_flow1">
        <omgdi:waypoint x="415.0" y="145.0"></omgdi:waypoint>
        <omgdi:waypoint x="460.0" y="145.0"></omgdi:waypoint>
      </bpmndi:BPMNEdge>
      <bpmndi:BPMNEdge bpmnElement="flow2" id="BPMNEdge_flow2">
        <omgdi:waypoint x="565.0" y="145.0"></omgdi:waypoint>
        <omgdi:waypoint x="610.0" y="145.0"></omgdi:waypoint>
      </bpmndi:BPMNEdge>
    </bpmndi:BPMNPlane>
  </bpmndi:BPMNDiagram>
</definitions>